paratest/__init__.py
paratest/__version__.py
paratest/__version__.py~
paratest/paratest.py
paratest/persistence.py
paratest/plugins.py
paratest/plugins/__init__.py
paratest/plugins/dummy.paratest
paratest/plugins/dummy.paratest~
paratest/plugins/dummy.py
paratest/plugins/dummy.py~
paratest/plugins/dummy.yapsy-plugin~
paratest/plugins/nunit.paratest
paratest/plugins/nunit.py
paratest-2.1.2.dist-info/DESCRIPTION.rst
paratest-2.1.2.dist-info/METADATA
paratest-2.1.2.dist-info/RECORD
paratest-2.1.2.dist-info/WHEEL
paratest-2.1.2.dist-info/entry_points.txt
paratest-2.1.2.dist-info/metadata.json
paratest-2.1.2.dist-info/top_level.txt
