Metadata-Version: 2.0
Name: paratest
Version: 2.1.2
Summary: Test paralelizer
Home-page: https://github.com/paratestproject/paratest
Author: Miguel Ángel García
Author-email: miguelangel.garcia@gmail.com
License: MIT
Keywords: parallel test
Platform: UNKNOWN
Classifier: Development Status :: 5 - Production/Stable
Classifier: Programming Language :: Python :: Implementation :: PyPy
Classifier: Programming Language :: Python :: Implementation :: CPython
Classifier: Programming Language :: Python :: 2.7
Classifier: Programming Language :: Python :: 3.4
Classifier: Programming Language :: Python :: 3.5
Classifier: Environment :: Console
Classifier: Intended Audience :: Developers
Classifier: License :: OSI Approved :: MIT License
Classifier: Operating System :: OS Independent
Classifier: Topic :: Software Development :: Libraries :: Application Frameworks
